{
  "content": "theorem distinct_keys_toList [EquivBEq \u03b1] [LawfulHashable \u03b1] :\n    m.toList.Pairwise (fun a b => (a.1 == b.1) = false) :=\n  DHashMap.Const.distinct_keys_toList\nsection monadic\nvariable {m : HashMap \u03b1 \u03b2}",
  "metadata": {
    "source": "/Users/mustafasameen/Documents/lean-autoformal/data/raw/lean4/src/Std/Data/HashMap/Lemmas.lean",
    "definition_type": "theorem",
    "parent_file": "/Users/mustafasameen/Documents/lean-autoformal/data/raw/lean4/src/Std/Data/HashMap/Lemmas.lean",
    "definition_name": "distinct_keys_toList",
    "has_proof": false
  }
}